sboxtools/Sbox.py
sboxtools/__init__.py
sboxtools-0.0.1.dist-info/METADATA
sboxtools-0.0.1.dist-info/WHEEL
sboxtools-0.0.1.dist-info/top_level.txt
sboxtools-0.0.1.dist-info/RECORD
